gen_gamma_coder/src/components/register.sv
`timescale 1ns/1ps

module register #(
    parameter SIZE = 8
) (
    input  logic clk, rst_n, set,
    input  logic [SIZE - 1 : 0] d,  
    output logic [SIZE - 1 : 0] q
);

always_ff @( posedge clk or negedge rst_n ) begin
    if (!rst_n) 
        q <= '0;
    else if (set) 
        q <= d;
    else 
        q <= q;
end

endmodule

gen_gamma_coder/src/components/full_sum.sv
module full_sum (
    input logic a, b, p0,
    output logic q,
    output logic g, p
);

assign q = (a ^ b) ^ p0;
assign g = a * b;
assign p = a + b;

endmodule

gen_gamma_coder/src/components/adder.sv
`timescale 1ns/1ps

module adder (
    input  logic a0, a1, a2, a3, a4, a5, a6, a7,
    input  logic b0, b1, b2, b3, b4, b5, b6, b7,
    output logic q0, q1, q2, q3, q4, q5, q6, q7, q8
);

logic CARRY_IN;
logic g0, g1, g2, g3, g4, g5, g6, g7;
logic p0, p1, p2, p3, p4, p5, p6, p7;

assign CARRY_IN = 0;

assign c1 = g0 + 
            p0 * CARRY_IN;
assign c2 = g1 + 
            p1 * g0 + 
            p1 * p0 * CARRY_IN;
assign c3 = g2 + 
            p2 * g1 + 
            p2 * p1 * g0 + 
            p2 * p1 * p0 * CARRY_IN;
assign c4 = g3 + 
            p3 * g2 + 
            p3 * p2 * g1 + 
            p3 * p2 * p1 * g0 + 
            p3 * p2 * p1 * p0 * CARRY_IN;
assign c5 = g4 + 
            p4 * g3 + 
            p4 * p3 * g2 + 
            p4 * p3 * p2 * g1 + 
            p4 * p3 * p2 * p1 * g0 + 
            p4 * p3 * p2 * p1 * p0 * CARRY_IN;
assign c6 = g5 + 
            p5 * g4 + 
            p5 * p4 * g3 + 
            p5 * p4 * p3 * g2 + 
            p5 * p4 * p3 * p2 * g1 + 
            p5 * p4 * p3 * p2 * p1 * g0 + 
            p5 * p4 * p3 * p2 * p1 * p0 * CARRY_IN;
assign c7 = g6 + 
            p6 * g5 + 
            p6 * p5 * g4 + 
            p6 * p5 * p4 * g3 + 
            p6 * p5 * p4 * p3 * g2 + 
            p6 * p5 * p4 * p3 * p2 * g1 + 
            p6 * p5 * p4 * p3 * p2 * p1 * g0 + 
            p6 * p5 * p4 * p3 * p2 * p1 * p0 * CARRY_IN;
assign c8 = g7 + 
            p7 * g6 + 
            p7 * p6 * g5 + 
            p7 * p6 * p5 * g4 + 
            p7 * p6 * p5 * p4 * g3 + 
            p7 * p6 * p5 * p4 * p3 * g2 + 
            p7 * p6 * p5 * p4 * p3 * p2 * g1 + 
            p7 * p6 * p5 * p4 * p3 * p2 * p1 * g0 + 
            p7 * p6 * p5 * p4 * p3 * p2 * p1 * p0 * CARRY_IN;

full_sum sum0(.a(a0), .b(b0), .p0(CARRY_IN), .q(q0), .g(g0), .p(p0));
full_sum sum1(.a(a1), .b(b1), .p0(c1),       .q(q1), .g(g1), .p(p1));
full_sum sum2(.a(a2), .b(b2), .p0(c2),       .q(q2), .g(g2), .p(p2));
full_sum sum3(.a(a3), .b(b3), .p0(c3),       .q(q3), .g(g3), .p(p3));
full_sum sum4(.a(a4), .b(b4), .p0(c4),       .q(q4), .g(g4), .p(p4));
full_sum sum5(.a(a5), .b(b5), .p0(c5),       .q(q5), .g(g5), .p(p5));
full_sum sum6(.a(a6), .b(b6), .p0(c6),       .q(q6), .g(g6), .p(p6));
full_sum sum7(.a(a7), .b(b7), .p0(c7),       .q(q7), .g(g7), .p(p7));

assign q8 = c8;

endmodule

gen_gamma_coder/src/components/inverter.sv
`timescale 1ns/1ps

module inverter #(
	parameter DELAY = 10
) (
	input  logic in,
	output logic out
);

assign #2 out = ~in;

endmodule

gen_gamma_coder/src/components/ring_oscillator.sv
`timescale 1ns/1ps

module ring_oscillator #(
    parameter DELAY = 5
) (
	input logic en,
	output logic f0, f1, f2, f3
);

logic [2 : 0] out_inv_3;
logic [4 : 0] out_inv_5;
logic [6 : 0] out_inv_7;
logic [8 : 0] out_inv_9;

genvar i;
generate
	
	for (i = 0; i < 2; i = i + 1) begin : inv_3
		inverter i0(.in(out_inv_3[i]), .out(out_inv_3[i + 1]));
	end
	nand #(DELAY + 5) (out_inv_3[0], out_inv_3[2], en);
	
	for (i = 0; i < 4; i = i + 1) begin : inv_5
		inverter i2(.in(out_inv_5[i]), .out(out_inv_5[i + 1]));
	end
	nand #(DELAY + 5) (out_inv_5[0], out_inv_5[4], en);
	
	for (i = 0; i < 6; i = i + 1) begin : inv_7
		inverter i4(.in(out_inv_7[i]), .out(out_inv_7[i + 1]));
	end
	nand #(DELAY + 5) (out_inv_7[0], out_inv_7[6], en);
	
	for (i = 0; i < 8; i = i + 1) begin : inv_9
		inverter #(.DELAY(DELAY)) i6(.in(out_inv_9[i]), .out(out_inv_9[i + 1]));
	end
	nand #(DELAY + 5) (out_inv_9[0], out_inv_9[8], en);
	
endgenerate

assign f0 = out_inv_3[2];
assign f1 = out_inv_5[4];
assign f2 = out_inv_7[6];
assign f3 = out_inv_9[8];

endmodule

gen_gamma_coder/src/components/xor_extender.sv
`timescale 1ns/1ps

module xor_extender (
    input  logic en,
    output logic [7 : 0] q
);
    
logic [3 : 0] w;

ring_oscillator run_ring_oscillator (
    .en(en), .f0(w[0]), .f1(w[1]), .f2(w[2]), .f3(w[3])
);

assign q = {
    w[0] ^ w[3],
    w[1] ^ w[2],
    w[0] ^ w[2],
    w[1] ^ w[3],
    w[0] ^ w[1],
    w[2] ^ w[3],
    w[0] ^ w[3],
    w[2] ^ w[3]
};
        
endmodule

gen_gamma_coder/src/gen_gamma_coder.sv
`timescale 1ns/1ps

module gen_gamma_coder #(
    parameter SIZE = 8
) (
    input  logic clk, rst_n, set0, set1, en,
    input  logic [SIZE - 1 : 0] id,  
    output logic [SIZE - 1 : 0] nk,
    output logic [SIZE : 0]     md
);

logic [24 : 0] w;


register saving_input_data (
    .clk(clk), .rst_n(rst_n), .set(set0),
    .d(id),  
    .q(w[7 : 0])
);

xor_extender extend_ring_oscillator_output (
    .en(en),
    .q(w[15 : 8])
);

register saving_noise_key (
    .clk(clk), .rst_n(rst_n), .set(set0),
    .d(w[15 : 8]),  
    .q(nk)
);

adder sum_two_list (
    .a0(nk[0]), .a1(nk[1]), .a2(nk[2]), .a3(nk[3]), .a4(nk[4]), .a5(nk[5]), .a6(nk[6]), .a7(nk[7]),
    .b0(w[0]),  .b1(w[1]),  .b2(w[2]),  .b3(w[3]),  .b4(w[4]),  .b5(w[5]),  .b6(w[6]),  .b7(w[7]),
    .q0(w[16]), .q1(w[17]), .q2(w[18]), .q3(w[19]), .q4(w[20]), .q5(w[21]), .q6(w[22]), .q7(w[23]), .q8(w[24])
);

register #(SIZE + 1) saving_mix_data (
    .clk(clk), .rst_n(rst_n), .set(set1),
    .d(w[24 : 16]),  
    .q(md)
);

endmodule

gen_gamma_coder/tb/tb_gen_gamma_coder.sv
`include "../src/gen_gamma_coder.sv"
`include "../src/components/register.sv"
`include "../src/components/adder.sv"
`include "../src/components/ring_oscillator.sv"
`include "../src/components/xor_extender.sv"
`include "../src/components/full_sum.sv"
`include "../src/components/inverter.sv"
`timescale 1ns/1ps

module tb_gen_gamma_coder;

localparam SIZE = 8;
logic clk, rst_n, set0, set1, en;
logic [SIZE - 1 : 0] id;  
logic [SIZE - 1 : 0] nk;
logic [SIZE : 0]     md;


gen_gamma_coder #(SIZE) tb (
    .clk(clk), .rst_n(rst_n), .set0(set0), .set1(set1), .en(en),
    .id(id),  
    .nk(nk),
    .md(md)
);


initial begin
    clk = 0;
    rst_n = 0;
    en = 0;
    id = $random;
    set0 = 0;
    set1 = 0;
#10  rst_n = 1;
#30 en = 1;
    set0 = 1;
#10 set1 = 1;
#40 set0 = 0;
    set1 = 0;
    rst_n = 1;
#10  rst_n = 0;
    set0 = 1;
    set1 = 1;
#40 set0 = 0;
    set1 = 0;
end

localparam CLK_PERIOD = 10;
always #(CLK_PERIOD / 2) clk = ~clk;

initial begin
    $dumpfile("tb_gen_gamma_coder.vcd");
    $dumpvars(0, tb_gen_gamma_coder);
    $monitor("time = %t; clk = %b, rst_n = %b, id = %d, md = %d, nk = %d", $time, clk, rst_n, id, md, nk);
    #500 $finish(2);
end

endmodule

gen_gamma_coder/tb/tb_gen_gamma_coder.vcd
$date
	Mon May 13 00:15:46 2024
$end
$version
	Icarus Verilog
$end
$timescale
	1ps
$end
$scope module tb_gen_gamma_coder $end
$var wire 8 ! nk [7:0] $end
$var wire 9 " md [8:0] $end
$var parameter 32 # CLK_PERIOD $end
$var parameter 32 $ SIZE $end
$var reg 1 % clk $end
$var reg 1 & en $end
$var reg 8 ' id [7:0] $end
$var reg 1 ( rst_n $end
$var reg 1 ) set0 $end
$var reg 1 * set1 $end
$scope module tb $end
$var wire 1 % clk $end
$var wire 1 & en $end
$var wire 8 + id [7:0] $end
$var wire 1 ( rst_n $end
$var wire 1 ) set0 $end
$var wire 1 * set1 $end
$var wire 25 , w [24:0] $end
$var wire 8 - nk [7:0] $end
$var wire 9 . md [8:0] $end
$var parameter 32 / SIZE $end
$scope module extend_ring_oscillator_output $end
$var wire 1 & en $end
$var wire 4 0 w [3:0] $end
$var wire 8 1 q [7:0] $end
$scope module run_ring_oscillator $end
$var wire 1 & en $end
$var wire 9 2 out_inv_9 [8:0] $end
$var wire 7 3 out_inv_7 [6:0] $end
$var wire 5 4 out_inv_5 [4:0] $end
$var wire 3 5 out_inv_3 [2:0] $end
$var wire 1 6 f3 $end
$var wire 1 7 f2 $end
$var wire 1 8 f1 $end
$var wire 1 9 f0 $end
$var parameter 32 : DELAY $end
$scope begin inv_3[0] $end
$var parameter 2 ; i $end
$scope module i0 $end
$var wire 1 < in $end
$var wire 1 = out $end
$var parameter 32 > DELAY $end
$upscope $end
$upscope $end
$scope begin inv_3[1] $end
$var parameter 2 ? i $end
$scope module i0 $end
$var wire 1 @ in $end
$var wire 1 A out $end
$var parameter 32 B DELAY $end
$upscope $end
$upscope $end
$scope begin inv_5[0] $end
$var parameter 2 C i $end
$scope module i2 $end
$var wire 1 D in $end
$var wire 1 E out $end
$var parameter 32 F DELAY $end
$upscope $end
$upscope $end
$scope begin inv_5[1] $end
$var parameter 2 G i $end
$scope module i2 $end
$var wire 1 H in $end
$var wire 1 I out $end
$var parameter 32 J DELAY $end
$upscope $end
$upscope $end
$scope begin inv_5[2] $end
$var parameter 3 K i $end
$scope module i2 $end
$var wire 1 L in $end
$var wire 1 M out $end
$var parameter 32 N DELAY $end
$upscope $end
$upscope $end
$scope begin inv_5[3] $end
$var parameter 3 O i $end
$scope module i2 $end
$var wire 1 P in $end
$var wire 1 Q out $end
$var parameter 32 R DELAY $end
$upscope $end
$upscope $end
$scope begin inv_7[0] $end
$var parameter 2 S i $end
$scope module i4 $end
$var wire 1 T in $end
$var wire 1 U out $end
$var parameter 32 V DELAY $end
$upscope $end
$upscope $end
$scope begin inv_7[1] $end
$var parameter 2 W i $end
$scope module i4 $end
$var wire 1 X in $end
$var wire 1 Y out $end
$var parameter 32 Z DELAY $end
$upscope $end
$upscope $end
$scope begin inv_7[2] $end
$var parameter 3 [ i $end
$scope module i4 $end
$var wire 1 \ in $end
$var wire 1 ] out $end
$var parameter 32 ^ DELAY $end
$upscope $end
$upscope $end
$scope begin inv_7[3] $end
$var parameter 3 _ i $end
$scope module i4 $end
$var wire 1 ` in $end
$var wire 1 a out $end
$var parameter 32 b DELAY $end
$upscope $end
$upscope $end
$scope begin inv_7[4] $end
$var parameter 4 c i $end
$scope module i4 $end
$var wire 1 d in $end
$var wire 1 e out $end
$var parameter 32 f DELAY $end
$upscope $end
$upscope $end
$scope begin inv_7[5] $end
$var parameter 4 g i $end
$scope module i4 $end
$var wire 1 h in $end
$var wire 1 i out $end
$var parameter 32 j DELAY $end
$upscope $end
$upscope $end
$scope begin inv_9[0] $end
$var parameter 2 k i $end
$scope module i6 $end
$var wire 1 l in $end
$var wire 1 m out $end
$var parameter 32 n DELAY $end
$upscope $end
$upscope $end
$scope begin inv_9[1] $end
$var parameter 2 o i $end
$scope module i6 $end
$var wire 1 p in $end
$var wire 1 q out $end
$var parameter 32 r DELAY $end
$upscope $end
$upscope $end
$scope begin inv_9[2] $end
$var parameter 3 s i $end
$scope module i6 $end
$var wire 1 t in $end
$var wire 1 u out $end
$var parameter 32 v DELAY $end
$upscope $end
$upscope $end
$scope begin inv_9[3] $end
$var parameter 3 w i $end
$scope module i6 $end
$var wire 1 x in $end
$var wire 1 y out $end
$var parameter 32 z DELAY $end
$upscope $end
$upscope $end
$scope begin inv_9[4] $end
$var parameter 4 { i $end
$scope module i6 $end
$var wire 1 | in $end
$var wire 1 } out $end
$var parameter 32 ~ DELAY $end
$upscope $end
$upscope $end
$scope begin inv_9[5] $end
$var parameter 4 !" i $end
$scope module i6 $end
$var wire 1 "" in $end
$var wire 1 #" out $end
$var parameter 32 $" DELAY $end
$upscope $end
$upscope $end
$scope begin inv_9[6] $end
$var parameter 4 %" i $end
$scope module i6 $end
$var wire 1 &" in $end
$var wire 1 '" out $end
$var parameter 32 (" DELAY $end
$upscope $end
$upscope $end
$scope begin inv_9[7] $end
$var parameter 4 )" i $end
$scope module i6 $end
$var wire 1 *" in $end
$var wire 1 +" out $end
$var parameter 32 ," DELAY $end
$upscope $end
$upscope $end
$upscope $end
$upscope $end
$scope module saving_input_data $end
$var wire 1 % clk $end
$var wire 8 -" d [7:0] $end
$var wire 1 ( rst_n $end
$var wire 1 ) set $end
$var parameter 32 ." SIZE $end
$var reg 8 /" q [7:0] $end
$upscope $end
$scope module saving_mix_data $end
$var wire 1 % clk $end
$var wire 9 0" d [8:0] $end
$var wire 1 ( rst_n $end
$var wire 1 * set $end
$var parameter 33 1" SIZE $end
$var reg 9 2" q [8:0] $end
$upscope $end
$scope module saving_noise_key $end
$var wire 1 % clk $end
$var wire 8 3" d [7:0] $end
$var wire 1 ( rst_n $end
$var wire 1 ) set $end
$var parameter 32 4" SIZE $end
$var reg 8 5" q [7:0] $end
$upscope $end
$scope module sum_two_list $end
$var wire 1 6" CARRY_IN $end
$var wire 1 7" a0 $end
$var wire 1 8" a1 $end
$var wire 1 9" a2 $end
$var wire 1 :" a3 $end
$var wire 1 ;" a4 $end
$var wire 1 <" a5 $end
$var wire 1 =" a6 $end
$var wire 1 >" a7 $end
$var wire 1 ?" b0 $end
$var wire 1 @" b1 $end
$var wire 1 A" b2 $end
$var wire 1 B" b3 $end
$var wire 1 C" b4 $end
$var wire 1 D" b5 $end
$var wire 1 E" b6 $end
$var wire 1 F" b7 $end
$var wire 1 G" q8 $end
$var wire 1 H" q7 $end
$var wire 1 I" q6 $end
$var wire 1 J" q5 $end
$var wire 1 K" q4 $end
$var wire 1 L" q3 $end
$var wire 1 M" q2 $end
$var wire 1 N" q1 $end
$var wire 1 O" q0 $end
$var wire 1 P" p7 $end
$var wire 1 Q" p6 $end
$var wire 1 R" p5 $end
$var wire 1 S" p4 $end
$var wire 1 T" p3 $end
$var wire 1 U" p2 $end
$var wire 1 V" p1 $end
$var wire 1 W" p0 $end
$var wire 1 X" g7 $end
$var wire 1 Y" g6 $end
$var wire 1 Z" g5 $end
$var wire 1 [" g4 $end
$var wire 1 \" g3 $end
$var wire 1 ]" g2 $end
$var wire 1 ^" g1 $end
$var wire 1 _" g0 $end
$var wire 1 `" c8 $end
$var wire 1 a" c7 $end
$var wire 1 b" c6 $end
$var wire 1 c" c5 $end
$var wire 1 d" c4 $end
$var wire 1 e" c3 $end
$var wire 1 f" c2 $end
$var wire 1 g" c1 $end
$scope module sum0 $end
$var wire 1 7" a $end
$var wire 1 ?" b $end
$var wire 1 6" p0 $end
$var wire 1 O" q $end
$var wire 1 W" p $end
$var wire 1 _" g $end
$upscope $end
$scope module sum1 $end
$var wire 1 8" a $end
$var wire 1 @" b $end
$var wire 1 g" p0 $end
$var wire 1 N" q $end
$var wire 1 V" p $end
$var wire 1 ^" g $end
$upscope $end
$scope module sum2 $end
$var wire 1 9" a $end
$var wire 1 A" b $end
$var wire 1 f" p0 $end
$var wire 1 M" q $end
$var wire 1 U" p $end
$var wire 1 ]" g $end
$upscope $end
$scope module sum3 $end
$var wire 1 :" a $end
$var wire 1 B" b $end
$var wire 1 e" p0 $end
$var wire 1 L" q $end
$var wire 1 T" p $end
$var wire 1 \" g $end
$upscope $end
$scope module sum4 $end
$var wire 1 ;" a $end
$var wire 1 C" b $end
$var wire 1 d" p0 $end
$var wire 1 K" q $end
$var wire 1 S" p $end
$var wire 1 [" g $end
$upscope $end
$scope module sum5 $end
$var wire 1 <" a $end
$var wire 1 D" b $end
$var wire 1 c" p0 $end
$var wire 1 J" q $end
$var wire 1 R" p $end
$var wire 1 Z" g $end
$upscope $end
$scope module sum6 $end
$var wire 1 =" a $end
$var wire 1 E" b $end
$var wire 1 b" p0 $end
$var wire 1 I" q $end
$var wire 1 Q" p $end
$var wire 1 Y" g $end
$upscope $end
$scope module sum7 $end
$var wire 1 >" a $end
$var wire 1 F" b $end
$var wire 1 a" p0 $end
$var wire 1 H" q $end
$var wire 1 P" p $end
$var wire 1 X" g $end
$upscope $end
$upscope $end
$upscope $end
$upscope $end
$enddefinitions $end
$comment Show the parameter values. $end
$dumpall
b1000 4"
b1001 1"
b1000 ."
b101 ,"
b111 )"
b101 ("
b110 %"
b101 $"
b101 !"
b101 ~
b100 {
b101 z
b11 w
b101 v
b10 s
b101 r
b1 o
b101 n
b0 k
b1010 j
b101 g
b1010 f
b100 c
b1010 b
b11 _
b1010 ^
b10 [
b1010 Z
b1 W
b1010 V
b0 S
b1010 R
b11 O
b1010 N
b10 K
b1010 J
b1 G
b1010 F
b0 C
b1010 B
b1 ?
b1010 >
b0 ;
b101 :
b1000 /
b1000 $
b1010 #
$end
#0
$dumpvars
0g"
0f"
0e"
0d"
0c"
0b"
0a"
0`"
0_"
0^"
0]"
0\"
0["
0Z"
0Y"
0X"
0W"
0V"
0U"
0T"
0S"
0R"
0Q"
0P"
0O"
0N"
0M"
0L"
0K"
0J"
0I"
0H"
0G"
0F"
0E"
0D"
0C"
0B"
0A"
0@"
0?"
0>"
0="
0<"
0;"
0:"
09"
08"
07"
06"
b0 5"
bx 3"
b0 2"
b0 0"
b0 /"
b100100 -"
x+"
x*"
x'"
x&"
x#"
x""
x}
x|
xy
xx
xu
xt
xq
xp
xm
xl
xi
xh
xe
xd
xa
x`
x]
x\
xY
xX
xU
xT
xQ
xP
xM
xL
xI
xH
xE
xD
xA
x@
x=
x<
x9
x8
x7
x6
bx 5
bx 4
bx 3
bx 2
bx 1
bx 0
b0 .
b0 -
b0xxxxxxxx00000000 ,
b100100 +
0*
0)
0(
b100100 '
0&
0%
b0 "
b0 !
$end
#5000
1%
#10000
1l
1T
1D
1<
0%
bx1 2
bx1 3
bx1 4
bx1 5
1(
#12000
0p
0X
0H
0@
bx01 2
0m
bx01 3
0U
bx01 4
0E
bx01 5
0=
#14000
1t
1\
1L
bx1 0
19
bx101 2
1q
bx101 3
1Y
bx101 4
1I
b101 5
1A
#15000
1%
#16000
0x
0`
0P
bx0101 2
0u
bx0101 3
0]
bx0101 4
0M
#18000
bx0xxx 3"
b0xxxx0xxx00000000 ,
bx0xxx 1
1|
1d
bx11 0
18
bx10101 2
1y
bx10101 3
1a
b10101 4
1Q
#20000
0""
0h
bx010101 2
0}
bx010101 3
0e
0%
#22000
bx00x0xxx 3"
b0x00x0xxx00000000 ,
bx00x0xxx 1
1&"
bx111 0
17
bx1010101 2
1#"
b1010101 3
1i
#24000
0*"
bx01010101 2
0'"
#25000
1%
#26000
b0 3"
b0 ,
b0 1
b1111 0
16
b101010101 2
1+"
#30000
0%
#35000
1%
#40000
0%
1)
1&
#45000
b100100 0"
1J"
1M"
1R"
1D"
1U"
1A"
b1001000000000000100100 ,
b100100 /"
1%
#50000
0<
0D
0T
0l
0%
b100 5
b10100 4
b1010100 3
b101010100 2
1*
#52000
1@
1H
1X
1p
b110 5
1=
b10110 4
1E
b1010110 3
1U
b101010110 2
1m
#54000
b10101010 3"
b1001001010101000100100 ,
b10101010 1
b1110 0
09
0L
0\
0t
b10 5
0A
b10010 4
0I
b1010010 3
0Y
b101010010 2
0q
#55000
1H"
0J"
b11001110 0"
1L"
1N"
b110011101010101000100100 ,
1I"
1P"
1>"
1b"
1Z"
0R"
1<"
1T"
1:"
1V"
18"
b10101010 !
b10101010 -
b10101010 5"
b100100 "
b100100 .
b100100 2"
1%
#56000
1P
1`
1x
b11010 4
1M
b1011010 3
1]
b101011010 2
1u
#58000
b11110010 3"
b110011101111001000100100 ,
b11110010 1
b1100 0
08
0d
0|
b1010 4
0Q
b1001010 3
0a
b101001010 2
0y
#60000
1h
1""
b1101010 3
1e
b101101010 2
1}
0%
#62000
b10010111 3"
b110011101001011100100100 ,
b10010111 1
b1000 0
07
0&"
b101010 3
0i
b100101010 2
0#"
#64000
1*"
1<
b110101010 2
1'"
b11 5
#65000
1J"
1K"
0M"
b10111011 0"
1O"
0I"
b101110111001011100100100 ,
1L"
0b"
0Z"
1R"
0<"
1S"
1;"
0T"
0:"
0d"
1e"
1]"
0U"
19"
1W"
17"
b11001110 "
b11001110 .
b11001110 2"
b10010111 !
b10010111 -
b10010111 5"
1%
#66000
b0 3"
b101110110000000000100100 ,
b0 1
b0 0
06
0@
b10101010 2
0+"
b1 5
0=
#68000
b10101010 3"
b101110111010101000100100 ,
b10101010 1
b1 0
19
1D
b101 5
1A
b1011 4
#70000
0H
b1001 4
0E
0%
#72000
1L
1T
b1101 4
1I
b101011 3
#74000
0P
0X
b101 4
0M
b101001 3
0U
#75000
0J"
0K"
1M"
b11001110 0"
0O"
1I"
b110011101010101000100100 ,
1L"
1b"
1Z"
0R"
1<"
0S"
0;"
1T"
1:"
0e"
0]"
1U"
09"
0W"
07"
b10101010 !
b10101010 -
b10101010 5"
b10111011 "
b10111011 .
b10111011 2"
1%
#76000
b11110010 3"
b110011101111001000100100 ,
b11110010 1
b11 0
18
1\
1l
b10101 4
1Q
b101101 3
1Y
b10101011 2
#78000
0`
0p
0<
b100101 3
0]
b10101001 2
0m
b100 5
#80000
1d
1t
1@
b110101 3
1a
b10101101 2
1q
b110 5
1=
0%
#82000
b1011000 3"
b110011100101100000100100 ,
b1011000 1
0h
0x
b10 0
09
b10101 3
0e
b10100101 2
0u
b10 5
0A
#84000
b111101 3"
b110011100011110100100100 ,
b111101 1
b110 0
17
1|
b1010101 3
1i
b10110101 2
1y
#85000
0H"
0M"
b1100001 0"
0N"
1O"
1J"
0K"
b11000010011110100100100 ,
0L"
0P"
0>"
1c"
1S"
1;"
1d"
1e"
1]"
0U"
19"
0V"
08"
1W"
17"
b11001110 "
b11001110 .
b11001110 2"
b111101 !
b111101 -
b111101 5"
1%
#86000
0""
0D
b10010101 2
0}
b10100 4
#88000
1&"
1H
b11010101 2
1#"
b10110 4
1E
#90000
0*"
0L
b1010101 2
0'"
b10010 4
0I
0%
0*
0)
#92000
b10101010 3"
b11000011010101000100100 ,
b10101010 1
b1110 0
16
1P
1<
b101010101 2
1+"
b11010 4
1M
b11 5
#94000
b11110010 3"
b11000011111001000100100 ,
b11110010 1
b1100 0
08
0@
0T
b1010 4
0Q
b1 5
0=
b1010100 3
#95000
1%
#96000
b1011000 3"
b11000010101100000100100 ,
b1011000 1
b1101 0
19
1X
b101 5
1A
b1010110 3
1U
#98000
0\
b1010010 3
0Y
#100000
0O"
b0 0"
0I"
0J"
0K"
0L"
0<"
0S"
0;"
0T"
0:"
09"
0W"
07"
0b"
0Z"
0R"
0D"
0c"
0d"
0e"
0]"
0U"
0A"
b0 "
b0 .
b0 2"
b0 !
b0 -
b0 5"
b101100000000000 ,
b0 /"
1`
b1011010 3
1]
0%
1*
1)
0(
#102000
0d
0l
b1001010 3
0a
b101010100 2
#104000
1h
1p
1D
b1101010 3
1e
b101010110 2
1m
b1011 4
#105000
1%
#106000
b111101 3"
b11110100000000 ,
b111101 1
b1001 0
07
0t
0H
0<
b101010 3
0i
b101010010 2
0q
b1001 4
0E
b100 5
#108000
1x
1L
1@
b101011010 2
1u
b1101 4
1I
b110 5
1=
#110000
b10010111 3"
b1001011100000000 ,
b10010111 1
0|
0P
b1000 0
09
b101001010 2
0y
b101 4
0M
b10 5
0A
0%
#112000
b11001111 3"
b1100111100000000 ,
b11001111 1
1""
b1010 0
18
b101101010 2
1}
b10101 4
1Q
#114000
0&"
b100101010 2
0#"
#115000
1%
#116000
1*"
1T
b110101010 2
1'"
b101011 3
#118000
b1011000 3"
b101100000000000 ,
b1011000 1
b10 0
06
0X
b10101010 2
0+"
b101001 3
0U
#120000
1\
1<
b101101 3
1Y
0%
b11 5
#122000
0`
0@
0D
b100101 3
0]
b1 5
0=
b10100 4
#124000
b11110010 3"
b1111001000000000 ,
b11110010 1
1d
b11 0
19
1H
b110101 3
1a
b101 5
1A
b10110 4
1E
#125000
1%
#126000
0h
0L
b10101 3
0e
b10010 4
0I
#128000
b10010111 3"
b1001011100000000 ,
b10010111 1
b111 0
17
1P
1l
b1010101 3
1i
b11010 4
1M
b10101011 2
#130000
b11001111 3"
b1100111100000000 ,
b11001111 1
b101 0
08
0p
b1010 4
0Q
b10101001 2
0m
0%
#132000
1t
b10101101 2
1q
#134000
0x
0<
b10100101 2
0u
b100 5
#135000
1%
#136000
1|
1@
b10110101 2
1y
b110 5
1=
#138000
b1100101 3"
b110010100000000 ,
b1100101 1
0""
b100 0
09
0T
b10010101 2
0}
b10 5
0A
b1010100 3
#140000
1&"
1X
1D
b11010101 2
1#"
b1010110 3
1U
0%
b1011 4
0*
0)
#142000
0*"
0\
0H
b1010101 2
0'"
b1010010 3
0Y
b1001 4
0E
#144000
b11110010 3"
b1111001000000000 ,
b11110010 1
b1100 0
16
1`
1L
b101010101 2
1+"
b1011010 3
1]
b1101 4
1I
#145000
1%
#146000
0d
0P
b1001010 3
0a
b101 4
0M
#148000
b10101010 3"
b1010101000000000 ,
b10101010 1
1h
b1110 0
18
1<
b1101010 3
1e
b10101 4
1Q
b11 5
#150000
b11001111 3"
b1100111100000000 ,
b11001111 1
b1010 0
07
0@
b101010 3
0i
b1 5
0=
0%
#152000
b1100101 3"
b110010100000000 ,
b1100101 1
b1011 0
19
b101 5
1A
#154000
0l
b101010100 2
#155000
1%
#156000
1p
b101010110 2
1m
#158000
0t
0D
b101010010 2
0q
b10100 4
#160000
1x
1H
1T
b101011010 2
1u
b10110 4
1E
0%
b101011 3
#162000
0|
0L
0X
0<
b101001010 2
0y
b10010 4
0I
b101001 3
0U
b100 5
#164000
1""
1P
1\
1@
b101101010 2
1}
b11010 4
1M
b101101 3
1Y
b110 5
1=
#165000
1%
#166000
b10010111 3"
b1001011100000000 ,
b10010111 1
0&"
08
0`
b1000 0
09
b100101010 2
0#"
b1010 4
0Q
b100101 3
0]
b10 5
0A
#168000
1*"
1d
b110101010 2
1'"
b110101 3
1a
#170000
b0 3"
b0 ,
b0 1
b0 0
06
0h
b10101010 2
0+"
b10101 3
0e
0%
#172000
b1100101 3"
b110010100000000 ,
b1100101 1
b100 0
17
b1010101 3
1i
#175000
1%
#176000
1D
1<
b1011 4
b11 5
#178000
0H
0@
b1001 4
0E
b1 5
0=
#180000
b11001111 3"
b1100111100000000 ,
b11001111 1
1L
b101 0
19
1l
b1101 4
1I
b101 5
1A
0%
b10101011 2
#182000
0P
0p
0T
b101 4
0M
b10101001 2
0m
b1010100 3
#184000
b10010111 3"
b1001011100000000 ,
b10010111 1
b111 0
18
1t
1X
b10101 4
1Q
b10101101 2
1q
b1010110 3
1U
#185000
1%
#186000
0x
0\
b10100101 2
0u
b1010010 3
0Y
#188000
1|
1`
b10110101 2
1y
b1011010 3
1]
#190000
0""
0d
0<
b10010101 2
0}
b1001010 3
0a
0%
b100 5
#192000
1&"
1h
1@
b11010101 2
1#"
b1101010 3
1e
b110 5
1=
#194000
b1011000 3"
b101100000000000 ,
b1011000 1
0*"
07
b10 0
09
0D
b1010101 2
0'"
b101010 3
0i
b10 5
0A
b10100 4
#195000
1%
#196000
b11001111 3"
b1100111100000000 ,
b11001111 1
b1010 0
16
1H
b101010101 2
1+"
b10110 4
1E
#198000
0L
b10010 4
0I
#200000
1P
b11010 4
1M
0%
#202000
b10010111 3"
b1001011100000000 ,
b10010111 1
b1000 0
08
b1010 4
0Q
#204000
1T
1<
b101011 3
b11 5
#205000
1%
#206000
0X
0@
0l
b101001 3
0U
b1 5
0=
b101010100 2
#208000
b111101 3"
b11110100000000 ,
b111101 1
1\
b1001 0
19
1p
b101101 3
1Y
b101 5
1A
b101010110 2
1m
#210000
0`
0t
b100101 3
0]
b101010010 2
0q
0%
#212000
1d
1x
1D
b110101 3
1a
b101011010 2
1u
b1011 4
#214000
0h
0|
0H
b10101 3
0e
b101001010 2
0y
b1001 4
0E
#215000
1%
#216000
b1011000 3"
b101100000000000 ,
b1011000 1
b1101 0
17
1""
1L
b1010101 3
1i
b101101010 2
1}
b1101 4
1I
#218000
0&"
0P
0<
b100101010 2
0#"
b101 4
0M
b100 5
#220000
b0 3"
b0 ,
b0 1
1*"
b1111 0
18
1@
b110101010 2
1'"
b10101 4
1Q
b110 5
1=
0%
#222000
b111101 3"
b11110100000000 ,
b111101 1
06
b110 0
09
b10101010 2
0+"
b10 5
0A
#225000
1%
#226000
0T
b1010100 3
#228000
1X
b1010110 3
1U
#230000
0\
0D
b1010010 3
0Y
0%
b10100 4
#232000
1`
1H
1l
1<
b1011010 3
1]
b10110 4
1E
b10101011 2
b11 5
#234000
0d
0L
0p
0@
b1001010 3
0a
b10010 4
0I
b10101001 2
0m
b1 5
0=
#235000
1%
#236000
b10010111 3"
b1001011100000000 ,
b10010111 1
1h
1P
1t
b111 0
19
b1101010 3
1e
b11010 4
1M
b10101101 2
1q
b101 5
1A
